ficus/__init__.py
ficus/manager.py
ficus-0.7.1.dist-info/LICENSE
ficus-0.7.1.dist-info/METADATA
ficus-0.7.1.dist-info/WHEEL
ficus-0.7.1.dist-info/top_level.txt
ficus-0.7.1.dist-info/RECORD
