Metadata-Version: 2.1
Name: ficus
Version: 0.7.1
Summary: context managers for matplotlib subplots
Home-page: https://github.com/camillescott/ficus
Author: Camille Scott
Author-email: camille.scott.w@gmail.com
License: BSD 3-Clause
Platform: UNKNOWN
Requires-Python: >=3.7
Requires-Dist: matplotlib (>=2.0)
Provides-Extra: tests
Requires-Dist: pytest ; extra == 'tests'
